excel_exporter/__init__.py
excel_exporter/action.py
excel_exporter/admin.py
excel_exporter/default.xls
excel_exporter/default.xlsx
excel_exporter/writer.py
excel_exporter-0.1.3.dist-info/LICENSE
excel_exporter-0.1.3.dist-info/METADATA
excel_exporter-0.1.3.dist-info/WHEEL
excel_exporter-0.1.3.dist-info/top_level.txt
excel_exporter-0.1.3.dist-info/RECORD
