Metadata-Version: 2.1
Name: excel-exporter
Version: 0.1.3
Summary: A Django library for exporting data.
Home-page: https://github.com/zhangyu836/django-excel-export
Author: Zhang Yu
Author-email: zhangyu836@gmail.com
License: BSD License
Keywords: django,Excel,xls,xlsx,spreadsheet,workbook,template
Platform: Any platform 
Requires-Dist: xltpl (>=0.9.2)
Requires-Dist: pydocxtpl (>=0.2.1)
Requires-Dist: six
